variable_admin/__init__.py
variable_admin/static/admin/css/autocomplete.css
variable_admin/static/admin/css/base.css
variable_admin/static/admin/css/changelists.css
variable_admin/static/admin/css/dashboard.css
variable_admin/static/admin/css/fonts.css
variable_admin/static/admin/css/forms.css
variable_admin/static/admin/css/login.css
variable_admin/static/admin/css/nav_sidebar.css
variable_admin/static/admin/css/responsive.css
variable_admin/static/admin/css/responsive_rtl.css
variable_admin/static/admin/css/rtl.css
variable_admin/static/admin/css/widgets.css
variable_admin/templates/admin/change_list.html
django_variable_admin-0.0.11.dist-info/LICENSE
django_variable_admin-0.0.11.dist-info/METADATA
django_variable_admin-0.0.11.dist-info/WHEEL
django_variable_admin-0.0.11.dist-info/top_level.txt
django_variable_admin-0.0.11.dist-info/RECORD
